databind/__init__.py
databind/mypy/__init__.py
databind/mypy/_mypy_dataclasses.py
databind/mypy/_plugin.py
databind.mypy-0.0.3.dist-info/LICENSE.txt
databind.mypy-0.0.3.dist-info/METADATA
databind.mypy-0.0.3.dist-info/WHEEL
databind.mypy-0.0.3.dist-info/top_level.txt
databind.mypy-0.0.3.dist-info/zip-safe
databind.mypy-0.0.3.dist-info/RECORD
