Metadata-Version: 2.1
Name: databind.mypy
Version: 0.0.3
Summary: MyPy plugin for the "databind" module.
Home-page: https://github.com/NiklasRosenstein/python-databind
Author: Niklas Rosenstein
Author-email: rosensteinniklas@gmail.com
License: MIT
Platform: UNKNOWN
Requires-Python: >=3.6.0,<4.0.0
Requires-Dist: mypy (<1.0.0,>=0.800.0)
